{
  "id": "3572761",
  "name": "HOUCLOUD",
  "font_family": "iconfont",
  "css_prefix_text": "icon-",
  "description": "",
  "glyphs": [
    {
      "icon_id": "6179181",
      "name": "任务",
      "font_class": "renwu2",
      "unicode": "e653",
      "unicode_decimal": 58963
    },
    {
      "icon_id": "624555",
      "name": "购物车添加",
      "font_class": "gouwuchetianjia",
      "unicode": "e650",
      "unicode_decimal": 58960
    },
    {
      "icon_id": "28527668",
      "name": "通知",
      "font_class": "tongzhi",
      "unicode": "ecd8",
      "unicode_decimal": 60632
    },
    {
      "icon_id": "28527673",
      "name": "钱包",
      "font_class": "qianbao2",
      "unicode": "ecd9",
      "unicode_decimal": 60633
    },
    {
      "icon_id": "28527688",
      "name": "购物",
      "font_class": "gouwu",
      "unicode": "ecdb",
      "unicode_decimal": 60635
    },
    {
      "icon_id": "9567113",
      "name": "feedback-line",
      "font_class": "feedback-line",
      "unicode": "e8eb",
      "unicode_decimal": 59627
    },
    {
      "icon_id": "10916978",
      "name": "feedback-fill",
      "font_class": "feedback-fill",
      "unicode": "e6bb",
      "unicode_decimal": 59067
    },
    {
      "icon_id": "5478608",
      "name": "image",
      "font_class": "image",
      "unicode": "e92e",
      "unicode_decimal": 59694
    },
    {
      "icon_id": "12669102",
      "name": "images",
      "font_class": "images",
      "unicode": "e64f",
      "unicode_decimal": 58959
    },
    {
      "icon_id": "22095372",
      "name": "image-sharp",
      "font_class": "image-sharp",
      "unicode": "e9c9",
      "unicode_decimal": 59849
    },
    {
      "icon_id": "1084634",
      "name": "help",
      "font_class": "help",
      "unicode": "e64c",
      "unicode_decimal": 58956
    },
    {
      "icon_id": "2142826",
      "name": "help",
      "font_class": "help1",
      "unicode": "e6a2",
      "unicode_decimal": 59042
    },
    {
      "icon_id": "6151227",
      "name": "unlock",
      "font_class": "unlock",
      "unicode": "e7fa",
      "unicode_decimal": 59386
    },
    {
      "icon_id": "6151228",
      "name": "lock",
      "font_class": "lock",
      "unicode": "e7fb",
      "unicode_decimal": 59387
    },
    {
      "icon_id": "26197330",
      "name": "文件管理-通用-2",
      "font_class": "wenjianguanli-tongyong-2",
      "unicode": "e64e",
      "unicode_decimal": 58958
    },
    {
      "icon_id": "24433540",
      "name": "管理员",
      "font_class": "guanliyuan2",
      "unicode": "e67d",
      "unicode_decimal": 59005
    },
    {
      "icon_id": "3590935",
      "name": "管理员",
      "font_class": "guanliyuan1",
      "unicode": "e649",
      "unicode_decimal": 58953
    },
    {
      "icon_id": "11372643",
      "name": "安全",
      "font_class": "anquan1",
      "unicode": "e8ab",
      "unicode_decimal": 59563
    },
    {
      "icon_id": "12331675",
      "name": "首页",
      "font_class": "shouye",
      "unicode": "e66b",
      "unicode_decimal": 58987
    },
    {
      "icon_id": "16065650",
      "name": "组织机构",
      "font_class": "zuzhijigou",
      "unicode": "e66e",
      "unicode_decimal": 58990
    },
    {
      "icon_id": "577346",
      "name": "列表形式",
      "font_class": "liebiaoxingshi",
      "unicode": "e742",
      "unicode_decimal": 59202
    },
    {
      "icon_id": "643850",
      "name": "安全",
      "font_class": "49",
      "unicode": "e63c",
      "unicode_decimal": 58940
    },
    {
      "icon_id": "722564",
      "name": "佣金",
      "font_class": "yongjin",
      "unicode": "e65a",
      "unicode_decimal": 58970
    },
    {
      "icon_id": "827644",
      "name": "列表",
      "font_class": "liebiao",
      "unicode": "e65e",
      "unicode_decimal": 58974
    },
    {
      "icon_id": "1249039",
      "name": "财务管理",
      "font_class": "caiwuguanli1",
      "unicode": "e63d",
      "unicode_decimal": 58941
    },
    {
      "icon_id": "1382704",
      "name": "商店5",
      "font_class": "shangdian",
      "unicode": "e65d",
      "unicode_decimal": 58973
    },
    {
      "icon_id": "2071528",
      "name": "独立访问",
      "font_class": "wiappfangwenliang",
      "unicode": "e693",
      "unicode_decimal": 59027
    },
    {
      "icon_id": "2855987",
      "name": "邀请",
      "font_class": "yaoqing",
      "unicode": "e655",
      "unicode_decimal": 58965
    },
    {
      "icon_id": "4700542",
      "name": "权限",
      "font_class": "authority",
      "unicode": "e642",
      "unicode_decimal": 58946
    },
    {
      "icon_id": "7171128",
      "name": "财务公开",
      "font_class": "caiwu",
      "unicode": "e644",
      "unicode_decimal": 58948
    },
    {
      "icon_id": "8325022",
      "name": "菜单财务",
      "font_class": "caidancaiwu",
      "unicode": "e647",
      "unicode_decimal": 58951
    },
    {
      "icon_id": "8655870",
      "name": "活动",
      "font_class": "huodong",
      "unicode": "e64d",
      "unicode_decimal": 58957
    },
    {
      "icon_id": "11882909",
      "name": "bg-synchronization",
      "font_class": "bg-synchronization",
      "unicode": "e648",
      "unicode_decimal": 58952
    },
    {
      "icon_id": "11891829",
      "name": "synchronization",
      "font_class": "synchronization",
      "unicode": "e677",
      "unicode_decimal": 58999
    },
    {
      "icon_id": "12331672",
      "name": "接口",
      "font_class": "jiekou",
      "unicode": "e66a",
      "unicode_decimal": 58986
    },
    {
      "icon_id": "12392041",
      "name": "同步",
      "font_class": "tongbu",
      "unicode": "e6fb",
      "unicode_decimal": 59131
    },
    {
      "icon_id": "15808916",
      "name": "多人-人群",
      "font_class": "duoren-renqun",
      "unicode": "e76a",
      "unicode_decimal": 59242
    },
    {
      "icon_id": "16137386",
      "name": "佣金管理",
      "font_class": "yongjinguanli",
      "unicode": "e7cd",
      "unicode_decimal": 59341
    },
    {
      "icon_id": "18072069",
      "name": "dashboard",
      "font_class": "dashboard",
      "unicode": "e7dd",
      "unicode_decimal": 59357
    },
    {
      "icon_id": "18171259",
      "name": "列表",
      "font_class": "list-v2-full",
      "unicode": "ea3b",
      "unicode_decimal": 59963
    },
    {
      "icon_id": "19673015",
      "name": "访问量",
      "font_class": "fangwenliang",
      "unicode": "e703",
      "unicode_decimal": 59139
    },
    {
      "icon_id": "22519167",
      "name": "人群",
      "font_class": "renqun",
      "unicode": "e798",
      "unicode_decimal": 59288
    },
    {
      "icon_id": "738192",
      "name": "安全",
      "font_class": "anquan",
      "unicode": "e639",
      "unicode_decimal": 58937
    },
    {
      "icon_id": "9384062",
      "name": "菜单",
      "font_class": "caidan",
      "unicode": "e63b",
      "unicode_decimal": 58939
    },
    {
      "icon_id": "9592764",
      "name": "公司",
      "font_class": "gongsi",
      "unicode": "e67b",
      "unicode_decimal": 59003
    },
    {
      "icon_id": "24858469",
      "name": "直播 电视",
      "font_class": "Rrl_s_080",
      "unicode": "e636",
      "unicode_decimal": 58934
    },
    {
      "icon_id": "28427024",
      "name": "购物车",
      "font_class": "gouwuche",
      "unicode": "e637",
      "unicode_decimal": 58935
    },
    {
      "icon_id": "1232412",
      "name": "实人认证",
      "font_class": "shirenrenzheng",
      "unicode": "e71f",
      "unicode_decimal": 59167
    },
    {
      "icon_id": "7171127",
      "name": "机关财务管理",
      "font_class": "caiwuguanli",
      "unicode": "e632",
      "unicode_decimal": 58930
    },
    {
      "icon_id": "7819605",
      "name": "统计分析",
      "font_class": "tongjifenxi",
      "unicode": "e633",
      "unicode_decimal": 58931
    },
    {
      "icon_id": "14184531",
      "name": "会员",
      "font_class": "bianzu16",
      "unicode": "e635",
      "unicode_decimal": 58933
    },
    {
      "icon_id": "146544",
      "name": "精选",
      "font_class": "jingxuanfuzhifuzhi",
      "unicode": "e627",
      "unicode_decimal": 58919
    },
    {
      "icon_id": "414851",
      "name": "商品管理",
      "font_class": "shangpinguanli",
      "unicode": "e631",
      "unicode_decimal": 58929
    },
    {
      "icon_id": "683385",
      "name": "积分商城",
      "font_class": "jifenshangcheng",
      "unicode": "e628",
      "unicode_decimal": 58920
    },
    {
      "icon_id": "1076756",
      "name": "商城",
      "font_class": "shangcheng",
      "unicode": "e62a",
      "unicode_decimal": 58922
    },
    {
      "icon_id": "2305511",
      "name": "收藏",
      "font_class": "shoucang",
      "unicode": "e62c",
      "unicode_decimal": 58924
    },
    {
      "icon_id": "4251753",
      "name": "商品",
      "font_class": "shangpin2",
      "unicode": "e64b",
      "unicode_decimal": 58955
    },
    {
      "icon_id": "4936652",
      "name": "fire-fill",
      "font_class": "fire-fill",
      "unicode": "e866",
      "unicode_decimal": 59494
    },
    {
      "icon_id": "4936668",
      "name": "eye-fill",
      "font_class": "eye-fill",
      "unicode": "e869",
      "unicode_decimal": 59497
    },
    {
      "icon_id": "4936669",
      "name": "like-fill",
      "font_class": "like-fill",
      "unicode": "e86a",
      "unicode_decimal": 59498
    },
    {
      "icon_id": "4936672",
      "name": "unlike-fill",
      "font_class": "unlike-fill",
      "unicode": "e86b",
      "unicode_decimal": 59499
    },
    {
      "icon_id": "4936982",
      "name": "HTML5-fill",
      "font_class": "HTML-fill",
      "unicode": "e881",
      "unicode_decimal": 59521
    },
    {
      "icon_id": "4954374",
      "name": "打赏",
      "font_class": "dashang1",
      "unicode": "e61a",
      "unicode_decimal": 58906
    },
    {
      "icon_id": "5643519",
      "name": "立即投递",
      "font_class": "lijitoudi",
      "unicode": "e61b",
      "unicode_decimal": 58907
    },
    {
      "icon_id": "6438266",
      "name": "地点",
      "font_class": "didian",
      "unicode": "e641",
      "unicode_decimal": 58945
    },
    {
      "icon_id": "6560954",
      "name": "金额",
      "font_class": "jine",
      "unicode": "e61c",
      "unicode_decimal": 58908
    },
    {
      "icon_id": "8092166",
      "name": "eye close-fill",
      "font_class": "eyeclose-fill",
      "unicode": "e8ff",
      "unicode_decimal": 59647
    },
    {
      "icon_id": "8092167",
      "name": "eye-close",
      "font_class": "eye-close",
      "unicode": "e900",
      "unicode_decimal": 59648
    },
    {
      "icon_id": "8574949",
      "name": "微信支付",
      "font_class": "weixinzhifu",
      "unicode": "e61d",
      "unicode_decimal": 58909
    },
    {
      "icon_id": "8797986",
      "name": "浏览",
      "font_class": "liulan",
      "unicode": "e7d0",
      "unicode_decimal": 59344
    },
    {
      "icon_id": "10471752",
      "name": "浏览",
      "font_class": "gongkai",
      "unicode": "e629",
      "unicode_decimal": 58921
    },
    {
      "icon_id": "11372685",
      "name": "扫一扫",
      "font_class": "saoyisao",
      "unicode": "e8b5",
      "unicode_decimal": 59573
    },
    {
      "icon_id": "11391544",
      "name": "浏览",
      "font_class": "liulan1",
      "unicode": "e638",
      "unicode_decimal": 58936
    },
    {
      "icon_id": "11594406",
      "name": "浏览",
      "font_class": "liulan2",
      "unicode": "e6b5",
      "unicode_decimal": 59061
    },
    {
      "icon_id": "14138563",
      "name": "地点",
      "font_class": "didian1",
      "unicode": "e678",
      "unicode_decimal": 59000
    },
    {
      "icon_id": "16050278",
      "name": "认证",
      "font_class": "renzheng2",
      "unicode": "e625",
      "unicode_decimal": 58917
    },
    {
      "icon_id": "19370410",
      "name": "zip",
      "font_class": "zip",
      "unicode": "e811",
      "unicode_decimal": 59409
    },
    {
      "icon_id": "20313952",
      "name": "时间",
      "font_class": "shijian",
      "unicode": "e61f",
      "unicode_decimal": 58911
    },
    {
      "icon_id": "22903739",
      "name": "白天模式",
      "font_class": "baitianmoshi",
      "unicode": "e769",
      "unicode_decimal": 59241
    },
    {
      "icon_id": "23357678",
      "name": "金额",
      "font_class": "jine1",
      "unicode": "e669",
      "unicode_decimal": 58985
    },
    {
      "icon_id": "24099306",
      "name": "实名认证",
      "font_class": "shimingrenzheng",
      "unicode": "e626",
      "unicode_decimal": 58918
    },
    {
      "icon_id": "26160862",
      "name": "服务",
      "font_class": "JC_028",
      "unicode": "e646",
      "unicode_decimal": 58950
    },
    {
      "icon_id": "26433316",
      "name": "编程",
      "font_class": "KJ_005",
      "unicode": "e676",
      "unicode_decimal": 58998
    },
    {
      "icon_id": "201648",
      "name": "3.1 时间",
      "font_class": "31shijian",
      "unicode": "e609",
      "unicode_decimal": 58889
    },
    {
      "icon_id": "480631",
      "name": "认证",
      "font_class": "renzheng",
      "unicode": "e699",
      "unicode_decimal": 59033
    },
    {
      "icon_id": "1117769",
      "name": "一起玩认证达人2",
      "font_class": "daren",
      "unicode": "e643",
      "unicode_decimal": 58947
    },
    {
      "icon_id": "1167177",
      "name": "认证",
      "font_class": "renzheng1",
      "unicode": "e640",
      "unicode_decimal": 58944
    },
    {
      "icon_id": "1287678",
      "name": "企业认证",
      "font_class": "qiyerenzheng",
      "unicode": "e60a",
      "unicode_decimal": 58890
    },
    {
      "icon_id": "2019071",
      "name": "已投递",
      "font_class": "yitoudi",
      "unicode": "e7b0",
      "unicode_decimal": 59312
    },
    {
      "icon_id": "2578451",
      "name": "实名",
      "font_class": "shiming",
      "unicode": "e60d",
      "unicode_decimal": 58893
    },
    {
      "icon_id": "2677238",
      "name": "打赏",
      "font_class": "dashang",
      "unicode": "e610",
      "unicode_decimal": 58896
    },
    {
      "icon_id": "3166363",
      "name": "自动模式(未激活)@2x",
      "font_class": "zidongmoshiweijihuox",
      "unicode": "e617",
      "unicode_decimal": 58903
    },
    {
      "icon_id": "3659216",
      "name": "夜晚模式",
      "font_class": "yewanmoshi",
      "unicode": "e671",
      "unicode_decimal": 58993
    },
    {
      "icon_id": "4111811",
      "name": "代码",
      "font_class": "code",
      "unicode": "e619",
      "unicode_decimal": 58905
    },
    {
      "icon_id": "4765866",
      "name": "message",
      "font_class": "message",
      "unicode": "e78b",
      "unicode_decimal": 59275
    },
    {
      "icon_id": "4765896",
      "name": "eye",
      "font_class": "eye",
      "unicode": "e78f",
      "unicode_decimal": 59279
    },
    {
      "icon_id": "4766512",
      "name": "property safety",
      "font_class": "propertysafety",
      "unicode": "e7c0",
      "unicode_decimal": 59328
    },
    {
      "icon_id": "4766513",
      "name": "safety certificate",
      "font_class": "safetycertificate",
      "unicode": "e7c1",
      "unicode_decimal": 59329
    },
    {
      "icon_id": "4766514",
      "name": "insurance ",
      "font_class": "insurance",
      "unicode": "e7c2",
      "unicode_decimal": 59330
    },
    {
      "icon_id": "4766692",
      "name": "like",
      "font_class": "like",
      "unicode": "e7c8",
      "unicode_decimal": 59336
    },
    {
      "icon_id": "4766693",
      "name": "unlike",
      "font_class": "unlike",
      "unicode": "e7c9",
      "unicode_decimal": 59337
    },
    {
      "icon_id": "4936460",
      "name": "fire",
      "font_class": "fire",
      "unicode": "e842",
      "unicode_decimal": 59458
    },
    {
      "icon_id": "4936522",
      "name": "message-fill",
      "font_class": "message-fill",
      "unicode": "e84a",
      "unicode_decimal": 59466
    },
    {
      "icon_id": "4936598",
      "name": "insurance-fill",
      "font_class": "insurance-fill",
      "unicode": "e856",
      "unicode_decimal": 59478
    },
    {
      "icon_id": "4936599",
      "name": "security scan-fill",
      "font_class": "securityscan-fill",
      "unicode": "e857",
      "unicode_decimal": 59479
    },
    {
      "icon_id": "4867083",
      "name": "筛选",
      "font_class": "shaixuan",
      "unicode": "e652",
      "unicode_decimal": 58962
    },
    {
      "icon_id": "8300814",
      "name": "筛选",
      "font_class": "shaixuan1",
      "unicode": "e607",
      "unicode_decimal": 58887
    },
    {
      "icon_id": "18174919",
      "name": "排序,降序",
      "font_class": "sort-down",
      "unicode": "ea4d",
      "unicode_decimal": 59981
    },
    {
      "icon_id": "18174920",
      "name": "排序,降序",
      "font_class": "sort-down-full",
      "unicode": "ea4e",
      "unicode_decimal": 59982
    },
    {
      "icon_id": "1305472",
      "name": "任务",
      "font_class": "renwu",
      "unicode": "e63f",
      "unicode_decimal": 58943
    },
    {
      "icon_id": "3978080",
      "name": "用户主账号管理",
      "font_class": "yonghuzhuzhanghaoguanli",
      "unicode": "e630",
      "unicode_decimal": 58928
    },
    {
      "icon_id": "8766122",
      "name": "任务",
      "font_class": "renwu1",
      "unicode": "e60c",
      "unicode_decimal": 58892
    },
    {
      "icon_id": "9599417",
      "name": "公司信息",
      "font_class": "gongsixinxi",
      "unicode": "e67c",
      "unicode_decimal": 59004
    },
    {
      "icon_id": "20567863",
      "name": "子账号管理",
      "font_class": "zizhanghaoguanli",
      "unicode": "e717",
      "unicode_decimal": 59159
    },
    {
      "icon_id": "18166694",
      "name": "抖音",
      "font_class": "douyin",
      "unicode": "e8db",
      "unicode_decimal": 59611
    },
    {
      "icon_id": "18166712",
      "name": "快手",
      "font_class": "kuaishou",
      "unicode": "e8dc",
      "unicode_decimal": 59612
    },
    {
      "icon_id": "26961180",
      "name": "巨量引擎",
      "font_class": "juliangyinqing",
      "unicode": "e679",
      "unicode_decimal": 59001
    },
    {
      "icon_id": "26961181",
      "name": "巨量千川",
      "font_class": "juliangqianchuan",
      "unicode": "e67a",
      "unicode_decimal": 59002
    },
    {
      "icon_id": "846526",
      "name": "销量预测",
      "font_class": "xiaoliangyuce",
      "unicode": "e88e",
      "unicode_decimal": 59534
    },
    {
      "icon_id": "848588",
      "name": "paixu",
      "font_class": "paixu",
      "unicode": "e623",
      "unicode_decimal": 58915
    },
    {
      "icon_id": "3769199",
      "name": "支付",
      "font_class": "zhifu",
      "unicode": "e8f9",
      "unicode_decimal": 59641
    },
    {
      "icon_id": "3946289",
      "name": "010-热度",
      "font_class": "-redu",
      "unicode": "e604",
      "unicode_decimal": 58884
    },
    {
      "icon_id": "10199170",
      "name": "解除",
      "font_class": "jiechu",
      "unicode": "e616",
      "unicode_decimal": 58902
    },
    {
      "icon_id": "14842935",
      "name": "粉丝",
      "font_class": "fensi",
      "unicode": "e6de",
      "unicode_decimal": 59102
    },
    {
      "icon_id": "16042904",
      "name": "客户销量@3x",
      "font_class": "kehuxiaoliang3x",
      "unicode": "e608",
      "unicode_decimal": 58888
    },
    {
      "icon_id": "16731262",
      "name": "解除关联",
      "font_class": "jiechuguanlian",
      "unicode": "e605",
      "unicode_decimal": 58885
    },
    {
      "icon_id": "18174901",
      "name": "排序",
      "font_class": "sort",
      "unicode": "ea4b",
      "unicode_decimal": 59979
    },
    {
      "icon_id": "26215887",
      "name": "排行榜",
      "font_class": "paihangbang2",
      "unicode": "e756",
      "unicode_decimal": 59222
    },
    {
      "icon_id": "397426",
      "name": "icon-top",
      "font_class": "xiangshang",
      "unicode": "e666",
      "unicode_decimal": 58982
    },
    {
      "icon_id": "974797",
      "name": "服务保障",
      "font_class": "fuwubaozhang",
      "unicode": "e6a0",
      "unicode_decimal": 59040
    },
    {
      "icon_id": "1346387",
      "name": "yly_赚积分 ",
      "font_class": "yly_zhuanjifen",
      "unicode": "e615",
      "unicode_decimal": 58901
    },
    {
      "icon_id": "5387592",
      "name": "箭头_页面_向右",
      "font_class": "jiantou_yemian_xiangyou",
      "unicode": "eb0b",
      "unicode_decimal": 60171
    },
    {
      "icon_id": "12183229",
      "name": "优惠券",
      "font_class": "youhuiquan-copy",
      "unicode": "e606",
      "unicode_decimal": 58886
    },
    {
      "icon_id": "17120506",
      "name": "向上",
      "font_class": "xiangshang-05",
      "unicode": "e667",
      "unicode_decimal": 58983
    },
    {
      "icon_id": "18610855",
      "name": "微笑",
      "font_class": "weixiao",
      "unicode": "e603",
      "unicode_decimal": 58883
    },
    {
      "icon_id": "900128",
      "name": "免费",
      "font_class": "mianfei1",
      "unicode": "e645",
      "unicode_decimal": 58949
    },
    {
      "icon_id": "975340",
      "name": "免费",
      "font_class": "mianfei",
      "unicode": "e62f",
      "unicode_decimal": 58927
    },
    {
      "icon_id": "1134337",
      "name": "收货",
      "font_class": "shouhuo",
      "unicode": "e684",
      "unicode_decimal": 59012
    },
    {
      "icon_id": "1400872",
      "name": "已完成",
      "font_class": "yiwancheng",
      "unicode": "e622",
      "unicode_decimal": 58914
    },
    {
      "icon_id": "6839508",
      "name": "发货",
      "font_class": "fahuo",
      "unicode": "e6b4",
      "unicode_decimal": 59060
    },
    {
      "icon_id": "9234828",
      "name": "已完成",
      "font_class": "yiwancheng1",
      "unicode": "e62b",
      "unicode_decimal": 58923
    },
    {
      "icon_id": "11520120",
      "name": "直播",
      "font_class": "zhibo",
      "unicode": "e74f",
      "unicode_decimal": 59215
    },
    {
      "icon_id": "25102289",
      "name": "快递代领",
      "font_class": "kuaididailing-01",
      "unicode": "e66f",
      "unicode_decimal": 58991
    },
    {
      "icon_id": "26506627",
      "name": "生产领料",
      "font_class": "shengchanlingliao",
      "unicode": "e62e",
      "unicode_decimal": 58926
    },
    {
      "icon_id": "20647591",
      "name": "icon_TikTok-square",
      "font_class": "icon_TikTok-square",
      "unicode": "e602",
      "unicode_decimal": 58882
    },
    {
      "icon_id": "1278122",
      "name": "下架",
      "font_class": "xiajia",
      "unicode": "e665",
      "unicode_decimal": 58981
    },
    {
      "icon_id": "1425584",
      "name": "Money",
      "font_class": "yichoujine",
      "unicode": "e60b",
      "unicode_decimal": 58891
    },
    {
      "icon_id": "5835469",
      "name": "钱包",
      "font_class": "qianbao1",
      "unicode": "e60f",
      "unicode_decimal": 58895
    },
    {
      "icon_id": "27876539",
      "name": "客服 客服中心",
      "font_class": "a-kefukefuzhongxin",
      "unicode": "e63a",
      "unicode_decimal": 58938
    },
    {
      "icon_id": "7629066",
      "name": "钱包",
      "font_class": "qianbao",
      "unicode": "e6b9",
      "unicode_decimal": 59065
    },
    {
      "icon_id": "5635075",
      "name": "user",
      "font_class": "user",
      "unicode": "f2dc",
      "unicode_decimal": 62172
    },
    {
      "icon_id": "7542688",
      "name": "24gl-bagFull",
      "font_class": "24gl-bagFull",
      "unicode": "e877",
      "unicode_decimal": 59511
    },
    {
      "icon_id": "7542726",
      "name": "24gf-bagFull",
      "font_class": "24gf-bagFull",
      "unicode": "e87f",
      "unicode_decimal": 59519
    },
    {
      "icon_id": "27364076",
      "name": "user",
      "font_class": "user1",
      "unicode": "ebbf",
      "unicode_decimal": 60351
    },
    {
      "icon_id": "12872653",
      "name": "公共-更多",
      "font_class": "gonggong-gengduo",
      "unicode": "e651",
      "unicode_decimal": 58961
    },
    {
      "icon_id": "796682",
      "name": "酒水",
      "font_class": "jiushui2",
      "unicode": "e64a",
      "unicode_decimal": 58954
    },
    {
      "icon_id": "6684",
      "name": "家庭清洁",
      "font_class": "jiatingqingji",
      "unicode": "e600",
      "unicode_decimal": 58880
    },
    {
      "icon_id": "173452",
      "name": "本地生活",
      "font_class": "bendishenghuo",
      "unicode": "e621",
      "unicode_decimal": 58913
    },
    {
      "icon_id": "651196",
      "name": "我的美食",
      "font_class": "wodemeishi0101",
      "unicode": "e61e",
      "unicode_decimal": 58910
    },
    {
      "icon_id": "798179",
      "name": "生活",
      "font_class": "icon",
      "unicode": "e66c",
      "unicode_decimal": 58988
    },
    {
      "icon_id": "3786023",
      "name": "爱生活-全部",
      "font_class": "weibiaoti-",
      "unicode": "e620",
      "unicode_decimal": 58912
    },
    {
      "icon_id": "3979176",
      "name": "化妆品",
      "font_class": "huazhuangpin",
      "unicode": "e612",
      "unicode_decimal": 58898
    },
    {
      "icon_id": "3979180",
      "name": "水果",
      "font_class": "shuiguo",
      "unicode": "e614",
      "unicode_decimal": 58900
    },
    {
      "icon_id": "3979427",
      "name": "数码产品",
      "font_class": "shumachanpin",
      "unicode": "e618",
      "unicode_decimal": 58904
    },
    {
      "icon_id": "7791010",
      "name": "服饰",
      "font_class": "fushi",
      "unicode": "e7ec",
      "unicode_decimal": 59372
    },
    {
      "icon_id": "8766469",
      "name": "奶瓶母婴",
      "font_class": "naipingmuying",
      "unicode": "e60e",
      "unicode_decimal": 58894
    },
    {
      "icon_id": "10563022",
      "name": "Tape measure",
      "font_class": "Tapemeasure",
      "unicode": "e6c4",
      "unicode_decimal": 59076
    },
    {
      "icon_id": "13500913",
      "name": "化妆品",
      "font_class": "huazhuangpin1",
      "unicode": "e601",
      "unicode_decimal": 58881
    },
    {
      "icon_id": "356464",
      "name": "商品",
      "font_class": "shangpin1",
      "unicode": "e624",
      "unicode_decimal": 58916
    },
    {
      "icon_id": "1486848",
      "name": "支付宝支付",
      "font_class": "zhifubaozhifu",
      "unicode": "e634",
      "unicode_decimal": 58932
    },
    {
      "icon_id": "2681714",
      "name": "微信支付",
      "font_class": "wxpay",
      "unicode": "e611",
      "unicode_decimal": 58897
    },
    {
      "icon_id": "11058856",
      "name": "小程序",
      "font_class": "xiaochengxu",
      "unicode": "e63e",
      "unicode_decimal": 58942
    },
    {
      "icon_id": "11372702",
      "name": "手机",
      "font_class": "shouji",
      "unicode": "e8b9",
      "unicode_decimal": 59577
    },
    {
      "icon_id": "11776584",
      "name": "选择",
      "font_class": "xuanze",
      "unicode": "e613",
      "unicode_decimal": 58899
    },
    {
      "icon_id": "15188194",
      "name": "app-store",
      "font_class": "app-store",
      "unicode": "e6c7",
      "unicode_decimal": 59079
    },
    {
      "icon_id": "26847637",
      "name": "评分",
      "font_class": "pingfen",
      "unicode": "e664",
      "unicode_decimal": 58980
    },
    {
      "icon_id": "577380",
      "name": "物流",
      "font_class": "wuliu",
      "unicode": "e75f",
      "unicode_decimal": 59231
    },
    {
      "icon_id": "4933193",
      "name": "火",
      "font_class": "huo",
      "unicode": "e6e1",
      "unicode_decimal": 59105
    },
    {
      "icon_id": "6129158",
      "name": "118订单、订单查询",
      "font_class": "dingdandingdanchaxun",
      "unicode": "e78a",
      "unicode_decimal": 59274
    },
    {
      "icon_id": "12591067",
      "name": "商品",
      "font_class": "shangpin",
      "unicode": "e748",
      "unicode_decimal": 59208
    },
    {
      "icon_id": "24684830",
      "name": "排行榜",
      "font_class": "paihangbang",
      "unicode": "e723",
      "unicode_decimal": 59171
    },
    {
      "icon_id": "24684951",
      "name": "排行榜",
      "font_class": "paihangbang1",
      "unicode": "e725",
      "unicode_decimal": 59173
    },
    {
      "icon_id": "29219747",
      "name": "火",
      "font_class": "hot",
      "unicode": "e62d",
      "unicode_decimal": 58925
    }
  ]
}
